{
  "title": "url-trim.shop",
  "slug": "url-trim-shop",
  "skills": ["Go", "React", "TypeScript", "MongoDB"],
  "summary": "This is a full-stack application I built as a practice while learning Go. It's a url shortener similar to bit.ly. Given a url, it shortens it and when users hit that shortened url, it redirects them to the original url.",
  "image": {
    "src": "/url-trim-shop.png",
    "alt": "screenshots of url-trim.shop landing page"
  },
  "links": [
    {
      "text": "View Live",
      "href": "https://url-trim-shop.herokuapp.com/"
    },
    {
      "text": "Github Repo",
      "href": "https://github.com/canrozanes/url-trim-shop"
    }
  ]
}
